model_predictions/README.md
model_predictions/__init__.py
model_predictions/app.py
model_predictions/constants.py
model_predictions/init_script.sh
model_predictions/requirements.txt
model_predictions/utils.py
refractBatch-1.24.1.dist-info/METADATA
refractBatch-1.24.1.dist-info/WHEEL
refractBatch-1.24.1.dist-info/top_level.txt
refractBatch-1.24.1.dist-info/RECORD
